coopihc/__init__.py
coopihc/agents/BaseAgent.py
coopihc/agents/ExampleAssistant.py
coopihc/agents/ExampleUser.py
coopihc/agents/__init__.py
coopihc/agents/lqrcontrollers/FHDT_LQRController.py
coopihc/agents/lqrcontrollers/IHCT_LQGController.py
coopihc/agents/lqrcontrollers/IHDT_LQRController.py
coopihc/agents/lqrcontrollers/LQRController.py
coopihc/agents/lqrcontrollers/__init__.py
coopihc/base/Space.py
coopihc/base/State.py
coopihc/base/StateElement.py
coopihc/base/__init__.py
coopihc/base/elements.py
coopihc/base/utils.py
coopihc/bundle/BaseBundle.py
coopihc/bundle/Bundle.py
coopihc/bundle/Simulator.py
coopihc/bundle/WsServer.py
coopihc/bundle/__init__.py
coopihc/bundle/wrappers/PipedTaskBundleWrapper.py
coopihc/bundle/wrappers/Train.py
coopihc/bundle/wrappers/__init__.py
coopihc/examples/basic_examples/agents_examples.py
coopihc/examples/basic_examples/bundle_examples.py
coopihc/examples/basic_examples/inference_examples.py
coopihc/examples/basic_examples/interactiontask_examples.py
coopihc/examples/basic_examples/observation_examples.py
coopihc/examples/basic_examples/policy_examples.py
coopihc/examples/basic_examples/space_examples.py
coopihc/examples/basic_examples/state_examples.py
coopihc/examples/basic_examples/stateelement_examples.py
coopihc/examples/simple_examples/assistant_has_user_model.py
coopihc/examples/simple_examples/exploit_rlnet.py
coopihc/examples/simple_examples/lqg_example.py
coopihc/examples/simple_examples/lqr_example.py
coopihc/examples/simple_examples/rl_sb3.py
coopihc/examples/simple_examples/saved_model.zip
coopihc/examples/simplepointing/assistants.py
coopihc/examples/simplepointing/envs.py
coopihc/examples/simplepointing/users.py
coopihc/examples/worked_out_examples/modules.py
coopihc/examples/worked_out_examples/train-and-execute.py
coopihc/examples/worked_out_examples/websockets/server.py
coopihc/helpers.py
coopihc/inference/BaseInferenceEngine.py
coopihc/inference/CascadedInferenceEngine.py
coopihc-0.0.2.dist-info/LICENSE
coopihc-0.0.2.dist-info/WHEEL
coopihc-0.0.2.dist-info/METADATA
coopihc-0.0.2.dist-info/RECORD
